odoo/addons/license_ocad/LICENSE
odoo/addons/license_ocad/README.rst
odoo/addons/license_ocad/__init__.py
odoo/addons/license_ocad/__manifest__.py
odoo/addons/license_ocad/data/ir_sequence.xml
odoo/addons/license_ocad/data/product_information_attribute_data.xml
odoo/addons/license_ocad/demo/demo.xml
odoo/addons/license_ocad/i18n/de_CH.po
odoo/addons/license_ocad/images/screen.png
odoo/addons/license_ocad/models/__init__.py
odoo/addons/license_ocad/models/license_activation.py
odoo/addons/license_ocad/models/license_license.py
odoo/addons/license_ocad/models/license_status.py
odoo/addons/license_ocad/models/ocad.py
odoo/addons/license_ocad/models/res_company.py
odoo/addons/license_ocad/models/res_config_settings.py
odoo/addons/license_ocad/readme/CONTRIBUTORS.md
odoo/addons/license_ocad/readme/DESCRIPTION.md
odoo/addons/license_ocad/readme/USAGE.md
odoo/addons/license_ocad/security/ir.model.access.csv
odoo/addons/license_ocad/security/security.xml
odoo/addons/license_ocad/static/description/icon.png
odoo/addons/license_ocad/static/description/index.html
odoo/addons/license_ocad/tests/TEST_INSTRUCTIONS.rst
odoo/addons/license_ocad/tests/test_ocad.py
odoo/addons/license_ocad/views/license_activation.xml
odoo/addons/license_ocad/views/license_license.xml
odoo/addons/license_ocad/views/license_status.xml
odoo/addons/license_ocad/views/res_config_settings.xml
odoo_addon_license_ocad-18.0.1.0.0.dist-info/METADATA
odoo_addon_license_ocad-18.0.1.0.0.dist-info/WHEEL
odoo_addon_license_ocad-18.0.1.0.0.dist-info/top_level.txt
odoo_addon_license_ocad-18.0.1.0.0.dist-info/RECORD
